FuzzyTM/FuzzyTM.py
FuzzyTM/__init__.py
FuzzyTM/fuzzy_tm.py
FuzzyTM/analysis/__init__.py
FuzzyTM/analysis/topic_specificity.py
FuzzyTM-2.0.9.dist-info/LICENSE
FuzzyTM-2.0.9.dist-info/METADATA
FuzzyTM-2.0.9.dist-info/WHEEL
FuzzyTM-2.0.9.dist-info/top_level.txt
FuzzyTM-2.0.9.dist-info/RECORD
