Metadata-Version: 2.1
Name: FuzzyTM
Version: 2.0.9
Summary: A Python package for Fuzzy Topic Models
Home-page: https://github.com/ERijck/FuzzyTM
Author: Emil Rijcken
Author-email: emil.rijcken@gmail.com
License: GNU General Public License v3.0
Platform: UNKNOWN
License-File: LICENSE
